llvd/__init__.py
llvd/app.py
llvd/cli.py
llvd/config.py
llvd/downloader.py
llvd/exceptions.py
llvd/process_io.py
llvd/utils.py
llvd/validators.py
llvd-3.1.0.dist-info/LICENSE
llvd-3.1.0.dist-info/METADATA
llvd-3.1.0.dist-info/WHEEL
llvd-3.1.0.dist-info/entry_points.txt
llvd-3.1.0.dist-info/top_level.txt
llvd-3.1.0.dist-info/RECORD
