Metadata-Version: 2.1
Name: llvd
Version: 3.1.0
Summary: Linkedin Learning Video Downloader CLI Tool
Home-page: https://github.com/knowbee/llvd.git
Author: Igwaneza Bruce
Author-email: knowbeeinc@gmail.com
License: UNKNOWN
Platform: any
Classifier: Environment :: Console
Classifier: Intended Audience :: Developers
Classifier: License :: OSI Approved :: MIT License
Classifier: Operating System :: OS Independent
Classifier: Programming Language :: Python :: 3
Requires-Python: >=3.6
License-File: LICENSE
Requires-Dist: beautifulsoup4 (>=4.12.2)
Requires-Dist: certifi (>=2023.7.22)
Requires-Dist: chardet (>=5.2.0)
Requires-Dist: click (>=8.1.7)
Requires-Dist: idna (>=3.4)
Requires-Dist: requests (>=2.31.0)
Requires-Dist: soupsieve (>=2.5)
Requires-Dist: tqdm (>=4.66.1)
Requires-Dist: urllib3 (>=2.0.7)
Requires-Dist: click-spinner (>=0.1.10)
Requires-Dist: texttable (>=1.7.0)
